Metadata-Version: 2.1
Name: pycovid-19
Version: 2.0
Summary: Covid Python plots and maps
Home-page: http://framagit.org/benjaminpillot/covid-19
Author: Benjamin Pillot
Author-email: benjaminpillot@riseup.net
License: GNU GPL v3.0
Requires-Python: ==3.9
License-File: LICENCE
